flask_encrypted_cookies_session/__init__.py
flask_encrypted_cookies_session/py.typed
flask_encrypted_cookies_session/session.py
flask_encrypted_cookies_session-0.2.4.dist-info/LICENSE
flask_encrypted_cookies_session-0.2.4.dist-info/METADATA
flask_encrypted_cookies_session-0.2.4.dist-info/WHEEL
flask_encrypted_cookies_session-0.2.4.dist-info/RECORD
