Metadata-Version: 2.1
Name: flask-encrypted-cookies-session
Version: 0.2.4
Summary: An encrypted cookie based session implementation for flask
Home-page: https://github.com/riton/flask-encrypted-cookies-session
License: CECILL-B
Keywords: flask,session,cookies,fernet
Author: Rémi Ferrand
Author-email: riton.github@gmail.com
Requires-Python: >=3.9,<4.0
Classifier: License :: CeCILL-B Free Software License Agreement (CECILL-B)
Classifier: Programming Language :: Python :: 3
Classifier: Programming Language :: Python :: 3.9
Classifier: Programming Language :: Python :: 3.10
Classifier: Programming Language :: Python :: 3.11
Requires-Dist: cryptography (>=40.0.2,<41.0.0)
Requires-Dist: flask (>=2.3.1,<3.0.0)
